{
  "item": [
    {
      "id": 2,
      "checked": false,
      "value": "we"
    },
    {
      "id": 4,
      "checked": false,
      "value": "we"
    },
    {
      "id": 5,
      "checked": false,
      "value": "w"
    },
    {
      "id": 6,
      "checked": false,
      "value": "e"
    },
    {
      "id": 7,
      "checked": false,
      "value": "w"
    },
    {
      "id": 8,
      "checked": false,
      "value": "ew"
    },
    {
      "id": 9,
      "checked": false,
      "value": "asdf"
    },
    {
      "id": 10,
      "checked": false,
      "value": "sdafasfdasdfasdf"
    },
    {
      "id": 11,
      "checked": false,
      "value": "afdasdfa"
    },
    {
      "id": 12,
      "checked": false,
      "value": "s"
    },
    {
      "id": 13,
      "checked": false,
      "value": "dfaswerejre ajdfja;lsf jklj lkjfldj sajf "
    },
    {
      "id": 14,
      "checked": false,
      "value": "There "
    },
    {
      "id": 15,
      "checked": false,
      "value": "There are a lot of place "
    },
    {
      "id": 16,
      "checked": false,
      "value": "there"
    },
    {
      "id": 17,
      "checked": false,
      "value": "There are a few thigns"
    }
  ]
}